pyav/RadarBook2_class.py
pyav/SignalProcessing_class.py
pyav/Wavelet_class.py
pyav/__init__.py
pyav/src/__init__.py
pyav/src/cmd_modules/Computation.py
pyav/src/cmd_modules/Connection.py
pyav/src/cmd_modules/DevDriver.py
pyav/src/cmd_modules/DevRcc1010.py
pyav/src/cmd_modules/DevRrn7745.py
pyav/src/cmd_modules/Rbk2.py
pyav/src/cmd_modules/Rbk2IfxTx2Rx16.py
pyav/src/cmd_modules/SeqTrig.py
pyav/src/cmd_modules/WgtTx4Rx16.py
pyav/src/cmd_modules/__init__.py
pyavlss2025-0.1.4.dist-info/METADATA
pyavlss2025-0.1.4.dist-info/WHEEL
pyavlss2025-0.1.4.dist-info/top_level.txt
pyavlss2025-0.1.4.dist-info/RECORD
